{
	"fa-icons": {
		"packageName":"Font Awsome Icons",
		"url":"http://fortawesome.github.io/Font-Awesome/icons/",
		"class":"fa",
		"icons": [
			{"className":"fa-bluetooth"},
			{"className":"fa-bluetooth-b"},
			{"className":"fa-codiepie"},
			{"className":"fa-credit-card-alt"},
			{"className":"fa-edge"},
			{"className":"fa-fort-awesome"},
			{"className":"fa-hashtag"},
			{"className":"fa-mixcloud"},
			{"className":"fa-modx"},
			{"className":"fa-pause-circle"},
			{"className":"fa-pause-circle-o"},
			{"className":"fa-percent"},
			{"className":"fa-product-hunt"},
			{"className":"fa-reddit-alien"},
			{"className":"fa-scribd"},
			{"className":"fa-shopping-bag"},
			{"className":"fa-shopping-basket"},
			{"className":"fa-stop-circle"},
			{"className":"fa-stop-circle-o"},
			{"className":"fa-usb"},
			{"className":"fa-adjust"},
			{"className":"fa-anchor"},
			{"className":"fa-archive"},
			{"className":"fa-area-chart"},
			{"className":"fa-arrows"},
			{"className":"fa-arrows-h"},
			{"className":"fa-arrows-v"},
			{"className":"fa-asterisk"},
			{"className":"fa-at"},
			{"className":"fa-automobile"},
			{"className":"fa-balance-scale"},
			{"className":"fa-ban"},
			{"className":"fa-bank"},
			{"className":"fa-bar-chart"},
			{"className":"fa-bar-chart-o"},
			{"className":"fa-barcode"},
			{"className":"fa-bars"},
			{"className":"fa-battery-0"},
			{"className":"fa-battery-1"},
			{"className":"fa-battery-2"},
			{"className":"fa-battery-3"},
			{"className":"fa-battery-4"},
			{"className":"fa-battery-empty"},
			{"className":"fa-battery-full"},
			{"className":"fa-battery-half"},
			{"className":"fa-battery-quarter"},
			{"className":"fa-battery-three-quarters"},
			{"className":"fa-bed"},
			{"className":"fa-beer"},
			{"className":"fa-bell"},
			{"className":"fa-bell-o"},
			{"className":"fa-bell-slash"},
			{"className":"fa-bell-slash-o"},
			{"className":"fa-bicycle"},
			{"className":"fa-binoculars"},
			{"className":"fa-birthday-cake"},
			{"className":"fa-bolt"},
			{"className":"fa-bomb"},
			{"className":"fa-book"},
			{"className":"fa-bookmark"},
			{"className":"fa-bookmark-o"},
			{"className":"fa-briefcase"},
			{"className":"fa-bug"},
			{"className":"fa-building"},
			{"className":"fa-building-o"},
			{"className":"fa-bullhorn"},
			{"className":"fa-bullseye"},
			{"className":"fa-bus"},
			{"className":"fa-cab"},
			{"className":"fa-calculator"},
			{"className":"fa-calendar"},
			{"className":"fa-calendar-check-o"},
			{"className":"fa-calendar-minus-o"},
			{"className":"fa-calendar-o"},
			{"className":"fa-calendar-plus-o"},
			{"className":"fa-calendar-times-o"},
			{"className":"fa-camera"},
			{"className":"fa-camera-retro"},
			{"className":"fa-car"},
			{"className":"fa-caret-square-o-down"},
			{"className":"fa-caret-square-o-left"},
			{"className":"fa-caret-square-o-right"},
			{"className":"fa-caret-square-o-up"},
			{"className":"fa-cart-arrow-down"},
			{"className":"fa-cart-plus"},
			{"className":"fa-cc"},
			{"className":"fa-certificate"},
			{"className":"fa-check"},
			{"className":"fa-check-circle"},
			{"className":"fa-check-circle-o"},
			{"className":"fa-check-square"},
			{"className":"fa-check-square-o"},
			{"className":"fa-child"},
			{"className":"fa-circle"},
			{"className":"fa-circle-o"},
			{"className":"fa-circle-o-notch"},
			{"className":"fa-circle-thin"},
			{"className":"fa-clock-o"},
			{"className":"fa-clone"},
			{"className":"fa-close"},
			{"className":"fa-cloud"},
			{"className":"fa-cloud-download"},
			{"className":"fa-cloud-upload"},
			{"className":"fa-code"},
			{"className":"fa-code-fork"},
			{"className":"fa-coffee"},
			{"className":"fa-cog"},
			{"className":"fa-cogs"},
			{"className":"fa-comment"},
			{"className":"fa-comment-o"},
			{"className":"fa-commenting"},
			{"className":"fa-commenting-o"},
			{"className":"fa-comments"},
			{"className":"fa-comments-o"},
			{"className":"fa-compass"},
			{"className":"fa-copyright"},
			{"className":"fa-creative-commons"},
			{"className":"fa-credit-card"},
			{"className":"fa-crop"},
			{"className":"fa-crosshairs"},
			{"className":"fa-cube"},
			{"className":"fa-cubes"},
			{"className":"fa-cutlery"},
			{"className":"fa-dashboard"},
			{"className":"fa-database"},
			{"className":"fa-desktop"},
			{"className":"fa-diamond"},
			{"className":"fa-dot-circle-o"},
			{"className":"fa-download"},
			{"className":"fa-edit"},
			{"className":"fa-ellipsis-h"},
			{"className":"fa-ellipsis-v"},
			{"className":"fa-envelope"},
			{"className":"fa-envelope-o"},
			{"className":"fa-envelope-square"},
			{"className":"fa-eraser"},
			{"className":"fa-exchange"},
			{"className":"fa-exclamation"},
			{"className":"fa-exclamation-circle"},
			{"className":"fa-exclamation-triangle"},
			{"className":"fa-external-link"},
			{"className":"fa-external-link-square"},
			{"className":"fa-eye"},
			{"className":"fa-eye-slash"},
			{"className":"fa-eyedropper"},
			{"className":"fa-fax"},
			{"className":"fa-feed"},
			{"className":"fa-female"},
			{"className":"fa-fighter-jet"},
			{"className":"fa-file-archive-o"},
			{"className":"fa-file-audio-o"},
			{"className":"fa-file-code-o"},
			{"className":"fa-file-excel-o"},
			{"className":"fa-file-image-o"},
			{"className":"fa-file-movie-o"},
			{"className":"fa-file-pdf-o"},
			{"className":"fa-file-photo-o"},
			{"className":"fa-file-picture-o"},
			{"className":"fa-file-powerpoint-o"},
			{"className":"fa-file-sound-o"},
			{"className":"fa-file-video-o"},
			{"className":"fa-file-word-o"},
			{"className":"fa-file-zip-o"},
			{"className":"fa-film"},
			{"className":"fa-filter"},
			{"className":"fa-fire"},
			{"className":"fa-fire-extinguisher"},
			{"className":"fa-flag"},
			{"className":"fa-flag-checkered"},
			{"className":"fa-flag-o"},
			{"className":"fa-flash"},
			{"className":"fa-flask"},
			{"className":"fa-folder"},
			{"className":"fa-folder-o"},
			{"className":"fa-folder-open"},
			{"className":"fa-folder-open-o"},
			{"className":"fa-frown-o"},
			{"className":"fa-futbol-o"},
			{"className":"fa-gamepad"},
			{"className":"fa-gavel"},
			{"className":"fa-gear"},
			{"className":"fa-gears"},
			{"className":"fa-gift"},
			{"className":"fa-glass"},
			{"className":"fa-globe"},
			{"className":"fa-graduation-cap"},
			{"className":"fa-group"},
			{"className":"fa-hand-grab-o"},
			{"className":"fa-hand-lizard-o"},
			{"className":"fa-hand-paper-o"},
			{"className":"fa-hand-peace-o"},
			{"className":"fa-hand-pointer-o"},
			{"className":"fa-hand-rock-o"},
			{"className":"fa-hand-scissors-o"},
			{"className":"fa-hand-spock-o"},
			{"className":"fa-hand-stop-o"},
			{"className":"fa-hdd-o"},
			{"className":"fa-headphones"},
			{"className":"fa-heart"},
			{"className":"fa-heart-o"},
			{"className":"fa-heartbeat"},
			{"className":"fa-history"},
			{"className":"fa-home"},
			{"className":"fa-hotel"},
			{"className":"fa-hourglass"},
			{"className":"fa-hourglass-1"},
			{"className":"fa-hourglass-2"},
			{"className":"fa-hourglass-3"},
			{"className":"fa-hourglass-end"},
			{"className":"fa-hourglass-half"},
			{"className":"fa-hourglass-o"},
			{"className":"fa-hourglass-start"},
			{"className":"fa-i-cursor"},
			{"className":"fa-image"},
			{"className":"fa-inbox"},
			{"className":"fa-industry"},
			{"className":"fa-info"},
			{"className":"fa-info-circle"},
			{"className":"fa-institution"},
			{"className":"fa-key"},
			{"className":"fa-keyboard-o"},
			{"className":"fa-language"},
			{"className":"fa-laptop"},
			{"className":"fa-leaf"},
			{"className":"fa-legal"},
			{"className":"fa-lemon-o"},
			{"className":"fa-level-down"},
			{"className":"fa-level-up"},
			{"className":"fa-life-bouy"},
			{"className":"fa-life-buoy"},
			{"className":"fa-life-ring"},
			{"className":"fa-life-saver"},
			{"className":"fa-lightbulb-o"},
			{"className":"fa-line-chart"},
			{"className":"fa-location-arrow"},
			{"className":"fa-lock"},
			{"className":"fa-magic"},
			{"className":"fa-magnet"},
			{"className":"fa-mail-forward"},
			{"className":"fa-mail-reply"},
			{"className":"fa-mail-reply-all"},
			{"className":"fa-male"},
			{"className":"fa-map"},
			{"className":"fa-map-marker"},
			{"className":"fa-map-o"},
			{"className":"fa-map-pin"},
			{"className":"fa-map-signs"},
			{"className":"fa-meh-o"},
			{"className":"fa-microphone"},
			{"className":"fa-microphone-slash"},
			{"className":"fa-minus"},
			{"className":"fa-minus-circle"},
			{"className":"fa-minus-square"},
			{"className":"fa-minus-square-o"},
			{"className":"fa-mobile"},
			{"className":"fa-mobile-phone"},
			{"className":"fa-money"},
			{"className":"fa-moon-o"},
			{"className":"fa-mortar-board"},
			{"className":"fa-motorcycle"},
			{"className":"fa-mouse-pointer"},
			{"className":"fa-music"},
			{"className":"fa-navicon"},
			{"className":"fa-newspaper-o"},
			{"className":"fa-object-group"},
			{"className":"fa-object-ungroup"},
			{"className":"fa-paint-brush"},
			{"className":"fa-paper-plane"},
			{"className":"fa-paper-plane-o"},
			{"className":"fa-paw"},
			{"className":"fa-pencil"},
			{"className":"fa-pencil-square"},
			{"className":"fa-pencil-square-o"},
			{"className":"fa-phone"},
			{"className":"fa-phone-square"},
			{"className":"fa-photo"},
			{"className":"fa-picture-o"},
			{"className":"fa-pie-chart"},
			{"className":"fa-plane"},
			{"className":"fa-plug"},
			{"className":"fa-plus"},
			{"className":"fa-plus-circle"},
			{"className":"fa-plus-square"},
			{"className":"fa-plus-square-o"},
			{"className":"fa-power-off"},
			{"className":"fa-print"},
			{"className":"fa-puzzle-piece"},
			{"className":"fa-qrcode"},
			{"className":"fa-question"},
			{"className":"fa-question-circle"},
			{"className":"fa-quote-left"},
			{"className":"fa-quote-right"},
			{"className":"fa-random"},
			{"className":"fa-recycle"},
			{"className":"fa-refresh"},
			{"className":"fa-registered"},
			{"className":"fa-remove"},
			{"className":"fa-reorder"},
			{"className":"fa-reply"},
			{"className":"fa-reply-all"},
			{"className":"fa-retweet"},
			{"className":"fa-road"},
			{"className":"fa-rocket"},
			{"className":"fa-rss"},
			{"className":"fa-rss-square"},
			{"className":"fa-search"},
			{"className":"fa-search-minus"},
			{"className":"fa-search-plus"},
			{"className":"fa-send"},
			{"className":"fa-send-o"},
			{"className":"fa-server"},
			{"className":"fa-share"},
			{"className":"fa-share-alt"},
			{"className":"fa-share-alt-square"},
			{"className":"fa-share-square"},
			{"className":"fa-share-square-o"},
			{"className":"fa-shield"},
			{"className":"fa-ship"},
			{"className":"fa-shopping-cart"},
			{"className":"fa-sign-in"},
			{"className":"fa-sign-out"},
			{"className":"fa-signal"},
			{"className":"fa-sitemap"},
			{"className":"fa-sliders"},
			{"className":"fa-smile-o"},
			{"className":"fa-soccer-ball-o"},
			{"className":"fa-sort"},
			{"className":"fa-sort-alpha-asc"},
			{"className":"fa-sort-alpha-desc"},
			{"className":"fa-sort-amount-asc"},
			{"className":"fa-sort-amount-desc"},
			{"className":"fa-sort-asc"},
			{"className":"fa-sort-desc"},
			{"className":"fa-sort-down"},
			{"className":"fa-sort-numeric-asc"},
			{"className":"fa-sort-numeric-desc"},
			{"className":"fa-sort-up"},
			{"className":"fa-space-shuttle"},
			{"className":"fa-spinner"},
			{"className":"fa-spoon"},
			{"className":"fa-square"},
			{"className":"fa-square-o"},
			{"className":"fa-star"},
			{"className":"fa-star-half"},
			{"className":"fa-star-half-empty"},
			{"className":"fa-star-half-full"},
			{"className":"fa-star-half-o"},
			{"className":"fa-star-o"},
			{"className":"fa-sticky-note"},
			{"className":"fa-sticky-note-o"},
			{"className":"fa-street-view"},
			{"className":"fa-suitcase"},
			{"className":"fa-sun-o"},
			{"className":"fa-support"},
			{"className":"fa-tablet"},
			{"className":"fa-tachometer"},
			{"className":"fa-tag"},
			{"className":"fa-tags"},
			{"className":"fa-tasks"},
			{"className":"fa-taxi"},
			{"className":"fa-television"},
			{"className":"fa-terminal"},
			{"className":"fa-thumb-tack"},
			{"className":"fa-thumbs-down"},
			{"className":"fa-thumbs-o-down"},
			{"className":"fa-thumbs-o-up"},
			{"className":"fa-thumbs-up"},
			{"className":"fa-ticket"},
			{"className":"fa-times"},
			{"className":"fa-times-circle"},
			{"className":"fa-times-circle-o"},
			{"className":"fa-tint"},
			{"className":"fa-toggle-down"},
			{"className":"fa-toggle-left"},
			{"className":"fa-toggle-off"},
			{"className":"fa-toggle-on"},
			{"className":"fa-toggle-right"},
			{"className":"fa-toggle-up"},
			{"className":"fa-trademark"},
			{"className":"fa-trash"},
			{"className":"fa-trash-o"},
			{"className":"fa-tree"},
			{"className":"fa-trophy"},
			{"className":"fa-truck"},
			{"className":"fa-tty"},
			{"className":"fa-tv"},
			{"className":"fa-umbrella"},
			{"className":"fa-university"},
			{"className":"fa-unlock"},
			{"className":"fa-unlock-alt"},
			{"className":"fa-unsorted"},
			{"className":"fa-upload"},
			{"className":"fa-user"},
			{"className":"fa-user-plus"},
			{"className":"fa-user-secret"},
			{"className":"fa-user-times"},
			{"className":"fa-users"},
			{"className":"fa-video-camera"},
			{"className":"fa-volume-down"},
			{"className":"fa-volume-off"},
			{"className":"fa-volume-up"},
			{"className":"fa-warning"},
			{"className":"fa-wheelchair"},
			{"className":"fa-wifi"},
			{"className":"fa-wrench"},
			{"className":"fa-hand-o-down"},
			{"className":"fa-hand-o-left"},
			{"className":"fa-hand-o-right"},
			{"className":"fa-hand-o-up"},
			{"className":"fa-ambulance"},
			{"className":"fa-subway"},
			{"className":"fa-train"},
			{"className":"fa-genderless"},
			{"className":"fa-intersex"},
			{"className":"fa-mars"},
			{"className":"fa-mars-double"},
			{"className":"fa-mars-stroke"},
			{"className":"fa-mars-stroke-h"},
			{"className":"fa-mars-stroke-v"},
			{"className":"fa-mercury"},
			{"className":"fa-neuter"},
			{"className":"fa-transgender"},
			{"className":"fa-transgender-alt"},
			{"className":"fa-venus"},
			{"className":"fa-venus-double"},
			{"className":"fa-venus-mars"},
			{"className":"fa-file"},
			{"className":"fa-file-o"},
			{"className":"fa-file-text"},
			{"className":"fa-file-text-o"},
			{"className":"fa-cc-amex"},
			{"className":"fa-cc-diners-club"},
			{"className":"fa-cc-discover"},
			{"className":"fa-cc-jcb"},
			{"className":"fa-cc-mastercard"},
			{"className":"fa-cc-paypal"},
			{"className":"fa-cc-stripe"},
			{"className":"fa-cc-visa"},
			{"className":"fa-google-wallet"},
			{"className":"fa-paypal"},
			{"className":"fa-bitcoin"},
			{"className":"fa-btc"},
			{"className":"fa-cny"},
			{"className":"fa-dollar"},
			{"className":"fa-eur"},
			{"className":"fa-euro"},
			{"className":"fa-gbp"},
			{"className":"fa-gg"},
			{"className":"fa-gg-circle"},
			{"className":"fa-ils"},
			{"className":"fa-inr"},
			{"className":"fa-jpy"},
			{"className":"fa-krw"},
			{"className":"fa-rmb"},
			{"className":"fa-rouble"},
			{"className":"fa-rub"},
			{"className":"fa-ruble"},
			{"className":"fa-rupee"},
			{"className":"fa-shekel"},
			{"className":"fa-sheqel"},
			{"className":"fa-try"},
			{"className":"fa-turkish-lira"},
			{"className":"fa-usd"},
			{"className":"fa-won"},
			{"className":"fa-yen"},
			{"className":"fa-align-center"},
			{"className":"fa-align-justify"},
			{"className":"fa-align-left"},
			{"className":"fa-align-right"},
			{"className":"fa-bold"},
			{"className":"fa-chain"},
			{"className":"fa-chain-broken"},
			{"className":"fa-clipboard"},
			{"className":"fa-columns"},
			{"className":"fa-copy"},
			{"className":"fa-cut"},
			{"className":"fa-dedent"},
			{"className":"fa-files-o"},
			{"className":"fa-floppy-o"},
			{"className":"fa-font"},
			{"className":"fa-header"},
			{"className":"fa-indent"},
			{"className":"fa-italic"},
			{"className":"fa-link"},
			{"className":"fa-list"},
			{"className":"fa-list-alt"},
			{"className":"fa-list-ol"},
			{"className":"fa-list-ul"},
			{"className":"fa-outdent"},
			{"className":"fa-paperclip"},
			{"className":"fa-paragraph"},
			{"className":"fa-paste"},
			{"className":"fa-repeat"},
			{"className":"fa-rotate-left"},
			{"className":"fa-rotate-right"},
			{"className":"fa-save"},
			{"className":"fa-scissors"},
			{"className":"fa-strikethrough"},
			{"className":"fa-subscript"},
			{"className":"fa-superscript"},
			{"className":"fa-table"},
			{"className":"fa-text-height"},
			{"className":"fa-text-width"},
			{"className":"fa-th"},
			{"className":"fa-th-large"},
			{"className":"fa-th-list"},
			{"className":"fa-underline"},
			{"className":"fa-undo"},
			{"className":"fa-unlink"},
			{"className":"fa-angle-double-down"},
			{"className":"fa-angle-double-left"},
			{"className":"fa-angle-double-right"},
			{"className":"fa-angle-double-up"},
			{"className":"fa-angle-down"},
			{"className":"fa-angle-left"},
			{"className":"fa-angle-right"},
			{"className":"fa-angle-up"},
			{"className":"fa-arrow-circle-down"},
			{"className":"fa-arrow-circle-left"},
			{"className":"fa-arrow-circle-o-down"},
			{"className":"fa-arrow-circle-o-left"},
			{"className":"fa-arrow-circle-o-right"},
			{"className":"fa-arrow-circle-o-up"},
			{"className":"fa-arrow-circle-right"},
			{"className":"fa-arrow-circle-up"},
			{"className":"fa-arrow-down"},
			{"className":"fa-arrow-left"},
			{"className":"fa-arrow-right"},
			{"className":"fa-arrow-up"},
			{"className":"fa-arrows-alt"},
			{"className":"fa-caret-down"},
			{"className":"fa-caret-left"},
			{"className":"fa-caret-right"},
			{"className":"fa-caret-up"},
			{"className":"fa-chevron-circle-down"},
			{"className":"fa-chevron-circle-left"},
			{"className":"fa-chevron-circle-right"},
			{"className":"fa-chevron-circle-up"},
			{"className":"fa-chevron-down"},
			{"className":"fa-chevron-left"},
			{"className":"fa-chevron-right"},
			{"className":"fa-chevron-up"},
			{"className":"fa-long-arrow-down"},
			{"className":"fa-long-arrow-left"},
			{"className":"fa-long-arrow-right"},
			{"className":"fa-long-arrow-up"},
			{"className":"fa-backward"},
			{"className":"fa-compress"},
			{"className":"fa-eject"},
			{"className":"fa-expand"},
			{"className":"fa-fast-backward"},
			{"className":"fa-fast-forward"},
			{"className":"fa-forward"},
			{"className":"fa-pause"},
			{"className":"fa-play"},
			{"className":"fa-play-circle"},
			{"className":"fa-play-circle-o"},
			{"className":"fa-step-backward"},
			{"className":"fa-step-forward"},
			{"className":"fa-stop"},
			{"className":"fa-youtube-play"},
			{"className":"fa-500px"},
			{"className":"fa-adn"},
			{"className":"fa-amazon"},
			{"className":"fa-android"},
			{"className":"fa-angellist"},
			{"className":"fa-apple"},
			{"className":"fa-behance"},
			{"className":"fa-behance-square"},
			{"className":"fa-bitbucket"},
			{"className":"fa-bitbucket-square"},
			{"className":"fa-black-tie"},
			{"className":"fa-buysellads"},
			{"className":"fa-chrome"},
			{"className":"fa-codepen"},
			{"className":"fa-connectdevelop"},
			{"className":"fa-contao"},
			{"className":"fa-css3"},
			{"className":"fa-dashcube"},
			{"className":"fa-delicious"},
			{"className":"fa-deviantart"},
			{"className":"fa-digg"},
			{"className":"fa-dribbble"},
			{"className":"fa-dropbox"},
			{"className":"fa-drupal"},
			{"className":"fa-empire"},
			{"className":"fa-expeditedssl"},
			{"className":"fa-facebook"},
			{"className":"fa-facebook-f"},
			{"className":"fa-facebook-official"},
			{"className":"fa-facebook-square"},
			{"className":"fa-firefox"},
			{"className":"fa-flickr"},
			{"className":"fa-fonticons"},
			{"className":"fa-forumbee"},
			{"className":"fa-foursquare"},
			{"className":"fa-ge"},
			{"className":"fa-get-pocket"},
			{"className":"fa-git"},
			{"className":"fa-git-square"},
			{"className":"fa-github"},
			{"className":"fa-github-alt"},
			{"className":"fa-github-square"},
			{"className":"fa-gittip"},
			{"className":"fa-google"},
			{"className":"fa-google-plus"},
			{"className":"fa-google-plus-square"},
			{"className":"fa-gratipay"},
			{"className":"fa-hacker-news"},
			{"className":"fa-houzz"},
			{"className":"fa-html5"},
			{"className":"fa-instagram"},
			{"className":"fa-internet-explorer"},
			{"className":"fa-ioxhost"},
			{"className":"fa-joomla"},
			{"className":"fa-jsfiddle"},
			{"className":"fa-lastfm"},
			{"className":"fa-lastfm-square"},
			{"className":"fa-leanpub"},
			{"className":"fa-linkedin"},
			{"className":"fa-linkedin-square"},
			{"className":"fa-linux"},
			{"className":"fa-maxcdn"},
			{"className":"fa-meanpath"},
			{"className":"fa-medium"},
			{"className":"fa-odnoklassniki"},
			{"className":"fa-odnoklassniki-square"},
			{"className":"fa-opencart"},
			{"className":"fa-openid"},
			{"className":"fa-opera"},
			{"className":"fa-optin-monster"},
			{"className":"fa-pagelines"},
			{"className":"fa-pied-piper"},
			{"className":"fa-pied-piper-alt"},
			{"className":"fa-pinterest"},
			{"className":"fa-pinterest-p"},
			{"className":"fa-pinterest-square"},
			{"className":"fa-qq"},
			{"className":"fa-ra"},
			{"className":"fa-rebel"},
			{"className":"fa-reddit"},
			{"className":"fa-reddit-square"},
			{"className":"fa-renren"},
			{"className":"fa-safari"},
			{"className":"fa-sellsy"},
			{"className":"fa-shirtsinbulk"},
			{"className":"fa-simplybuilt"},
			{"className":"fa-skyatlas"},
			{"className":"fa-skype"},
			{"className":"fa-slack"},
			{"className":"fa-slideshare"},
			{"className":"fa-soundcloud"},
			{"className":"fa-spotify"},
			{"className":"fa-stack-exchange"},
			{"className":"fa-stack-overflow"},
			{"className":"fa-steam"},
			{"className":"fa-steam-square"},
			{"className":"fa-stumbleupon"},
			{"className":"fa-stumbleupon-circle"},
			{"className":"fa-tencent-weibo"},
			{"className":"fa-trello"},
			{"className":"fa-tripadvisor"},
			{"className":"fa-tumblr"},
			{"className":"fa-tumblr-square"},
			{"className":"fa-twitch"},
			{"className":"fa-twitter"},
			{"className":"fa-twitter-square"},
			{"className":"fa-viacoin"},
			{"className":"fa-vimeo"},
			{"className":"fa-vimeo-square"},
			{"className":"fa-vine"},
			{"className":"fa-vk"},
			{"className":"fa-wechat"},
			{"className":"fa-weibo"},
			{"className":"fa-weixin"},
			{"className":"fa-whatsapp"},
			{"className":"fa-wikipedia-w"},
			{"className":"fa-windows"},
			{"className":"fa-wordpress"},
			{"className":"fa-xing"},
			{"className":"fa-xing-square"},
			{"className":"fa-y-combinator"},
			{"className":"fa-y-combinator-square"},
			{"className":"fa-yahoo"},
			{"className":"fa-yc"},
			{"className":"fa-yc-square"},
			{"className":"fa-yelp"},
			{"className":"fa-youtube"},
			{"className":"fa-youtube-square"},
			{"className":"fa-h-square"},
			{"className":"fa-hospital-o"},
			{"className":"fa-medkit"},
			{"className":"fa-stethoscope"},
			{"className":"fa-user-md"}
		]
	},
	"o365i-icons": {
		"packageName":"MS Office/Office365 Icons",
		"url":"http://spo365icons.azurewebsites.net/",
		"class":"o365i",
		"icons":[
			{"className":"o365i-circle", "content":"\\e000"},
			{"className":"o365i-circle2", "content":"\\e001"},
			{"className":"o365i-crossbox", "content":"\\e002"},
			{"className":"o365i-star", "content":"\\e003"},
			{"className":"o365i-plus", "content":"\\e004"},
			{"className":"o365i-minus", "content":"\\e005"},
			{"className":"o365i-question", "content":"\\e006"},
			{"className":"o365i-exclamation", "content":"\\e007"},
			{"className":"o365i-person", "content":"\\e008"},
			{"className":"o365i-mail", "content":"\\e009"},
			{"className":"o365i-info", "content":"\\e00a"},
			{"className":"o365i-warning", "content":"\\e00b"},
			{"className":"o365i-critical", "content":"\\e00c"},
			{"className":"o365i-mailopened", "content":"\\e00d"},
			{"className":"o365i-people", "content":"\\e00e"},
			{"className":"o365i-notification", "content":"\\e010"},
			{"className":"o365i-calendar", "content":"\\e011"},
			{"className":"o365i-calendarclockitem", "content":"\\e012"},
			{"className":"o365i-calendaritem", "content":"\\e013"},
			{"className":"o365i-folder", "content":"\\e014"},
			{"className":"o365i-files", "content":"\\e015"},
			{"className":"o365i-onedrive", "content":"\\e016"},
			{"className":"o365i-comment", "content":"\\e017"},
			{"className":"o365i-exit", "content":"\\e018"},
			{"className":"o365i-menu", "content":"\\e019"},
			{"className":"o365i-week", "content":"\\e01a"},
			{"className":"o365i-weekday", "content":"\\e01b"},
			{"className":"o365i-day", "content":"\\e01c"},
			{"className":"o365i-fowardfolder", "content":"\\e01d"},
			{"className":"o365i-windowdock", "content":"\\e01e"},
			{"className":"o365i-windowseparate", "content":"\\e01f"},
			{"className":"o365i-hamburger", "content":"\\e020"},
			{"className":"o365i-home", "content":"\\e021"},
			{"className":"o365i-webfav", "content":"\\e022"},
			{"className":"o365i-phone", "content":"\\e023"},
			{"className":"o365i-email", "content":"\\e024"},
			{"className":"o365i-save", "content":"\\e025"},
			{"className":"o365i-delete", "content":"\\e026"},
			{"className":"o365i-edit", "content":"\\e027"},
			{"className":"o365i-flag", "content":"\\e028"},
			{"className":"o365i-reply", "content":"\\e029"},
			{"className":"o365i-tiles", "content":"\\e02a"},
			{"className":"o365i-voicemail", "content":"\\e02b"},
			{"className":"o365i-play", "content":"\\e02c"},
			{"className":"o365i-pause", "content":"\\e02d"},
			{"className":"o365i-webadd", "content":"\\e02e"},
			{"className":"o365i-webperson", "content":"\\e02f"},
			{"className":"o365i-replyall", "content":"\\e030"},
			{"className":"o365i-attachment", "content":"\\e031"},
			{"className":"o365i-donotenter", "content":"\\e032"},
			{"className":"o365i-pin", "content":"\\e033"},
			{"className":"o365i-refresh", "content":"\\e034"},
			{"className":"o365i-gear", "content":"\\e035"},
			{"className":"o365i-smile", "content":"\\e036"},
			{"className":"o365i-i", "content":"\\e037"},
			{"className":"o365i-lock", "content":"\\e038"},
			{"className":"o365i-magnifiyingglass", "content":"\\e039"},
			{"className":"o365i-norefresh", "content":"\\e03b"},
			{"className":"o365i-tasks", "content":"\\e040"},
			{"className":"o365i-check", "content":"\\e041"},
			{"className":"o365i-x", "content":"\\e042"},
			{"className":"o365i-unlike", "content":"\\e043"},
			{"className":"o365i-like", "content":"\\e044"},
			{"className":"o365i-ellipses", "content":"\\e045"},
			{"className":"o365i-bullet", "content":"\\e046"},
			{"className":"o365i-up", "content":"\\e047"},
			{"className":"o365i-down", "content":"\\e048"},
			{"className":"o365i-left", "content":"\\e049"},
			{"className":"o365i-right", "content":"\\e04a"},
			{"className":"o365i-downunderline", "content":"\\e04b"},
			{"className":"o365i-rightturn", "content":"\\e04c"},
			{"className":"o365i-microphone", "content":"\\e04f"},
			{"className":"o365i-up2", "content":"\\e051"},
			{"className":"o365i-down2", "content":"\\e052"},
			{"className":"o365i-left2", "content":"\\e053"},
			{"className":"o365i-right2", "content":"\\e054"},
			{"className":"o365i-office", "content":"\\e055"},
			{"className":"o365i-office365", "content":"\\e056"},
			{"className":"o365i-office365preview", "content":"\\e057"},
			{"className":"o365i-topleft", "content":"\\e05a"},
			{"className":"o365i-topright", "content":"\\e05b"},
			{"className":"o365i-bottomright", "content":"\\e05c"},
			{"className":"o365i-bottomleft", "content":"\\e05d"},
			{"className":"o365i-app", "content":"\\e060"},
			{"className":"o365i-officestore", "content":"\\e061"},
			{"className":"o365i-outlook", "content":"\\e062"},
			{"className":"o365i-project", "content":"\\e063"},
			{"className":"o365i-yammer", "content":"\\e064"},
			{"className":"o365i-sydney", "content":"\\e065"},
			{"className":"o365i-lync", "content":"\\e066"},
			{"className":"o365i-postit", "content":"\\e06a"},
			{"className":"o365i-postitleftarrow", "content":"\\e06b"},
			{"className":"o365i-postitrightarrow", "content":"\\e06c"},
			{"className":"o365i-key", "content":"\\e06f"},
			{"className":"o365i-carousel", "content":"\\e070"},
			{"className":"o365i-checkboxrefresh", "content":"\\e071"},
			{"className":"o365i-sharepoint", "content":"\\e072"},
			{"className":"o365i-unstar", "content":"\\e073"},
			{"className":"o365i-topunderline", "content":"\\e076"},
			{"className":"o365i-wrench", "content":"\\e077"},
			{"className":"o365i-share", "content":"\\e078"},
			{"className":"o365i-fileleftarrow", "content":"\\e079"},
			{"className":"o365i-filerightarrow", "content":"\\e07a"},
			{"className":"o365i-personaward", "content":"\\e080"},
			{"className":"o365i-gearwrench", "content":"\\e081"},
			{"className":"o365i-microsoft", "content":"\\e083"},
			{"className":"o365i-uturn", "content":"\\e084"},
			{"className":"o365i-updown", "content":"\\e085"},
			{"className":"o365i-personadd", "content":"\\e086"},
			{"className":"o365i-up3", "content":"\\e087"},
			{"className":"o365i-down3", "content":"\\e088"},
			{"className":"o365i-left3", "content":"\\e089"},
			{"className":"o365i-right3", "content":"\\e08a"},
			{"className":"o365i-graph", "content":"\\e08b"},
			{"className":"o365i-peopleadd", "content":"\\e08c"},
			{"className":"o365i-newsfeed", "content":"\\e08d"},
			{"className":"o365i-notebook", "content":"\\e08e"},
			{"className":"o365i-link", "content":"\\e08f"},
			{"className":"o365i-up4", "content":"\\e090"},
			{"className":"o365i-down4", "content":"\\e091"},
			{"className":"o365i-left4", "content":"\\e092"},
			{"className":"o365i-right4", "content":"\\e093"},
			{"className":"o365i-broom", "content":"\\e09a"},
			{"className":"o365i-filetraydown", "content":"\\e09c"},
			{"className":"o365i-filetrayx", "content":"\\e09d"},
			{"className":"o365i-personx", "content":"\\e09e"},
			{"className":"o365i-rightarrowlist", "content":"\\e0a0"},
			{"className":"o365i-leftarrowlist", "content":"\\e0a1"},
			{"className":"o365i-checklist", "content":"\\e0a2"},
			{"className":"o365i-peoplex", "content":"\\e0a3"},
			{"className":"o365i-arrowinwards", "content":"\\e0a4"},
			{"className":"o365i-arrowoutwards", "content":"\\e0a5"},
			{"className":"o365i-calendaritemx", "content":"\\e0a6"},
			{"className":"o365i-calendaritemarrow", "content":"\\e0a7"},
			{"className":"o365i-calendaritemdown", "content":"\\e0a9"},
			{"className":"o365i-doorarrow", "content":"\\e0aa"},
			{"className":"o365i-voiceleftarrow", "content":"\\e0ac"},
			{"className":"o365i-voicerightarrow", "content":"\\e0ad"},
			{"className":"o365i-ribbon", "content":"\\e0af"},
			{"className":"o365i-contactcard", "content":"\\e0b0"},
			{"className":"o365i-eye", "content":"\\e0b1"},
			{"className":"o365i-glasses", "content":"\\e0b2"},
			{"className":"o365i-office365chinese", "content":"\\e0b3"},
			{"className":"o365i-access", "content":"\\e0b4"},
			{"className":"o365i-excel", "content":"\\e0b5"},
			{"className":"o365i-onenote", "content":"\\e0b7"},
			{"className":"o365i-powerpoint", "content":"\\e0b8"},
			{"className":"o365i-word", "content":"\\e0b9"},
			{"className":"o365i-print", "content":"\\e100"},
			{"className":"o365i-exit2", "content":"\\e101"},
			{"className":"o365i-postitpinned", "content":"\\e102"},
			{"className":"o365i-aside", "content":"\\e103"},
			{"className":"o365i-pushbutton", "content":"\\e104"},
			{"className":"o365i-clock", "content":"\\e105"},
			{"className":"o365i-fax", "content":"\\e106"},
			{"className":"o365i-event", "content":"\\e110"},
			{"className":"o365i-numpad", "content":"\\e111"},
			{"className":"o365i-callarrows", "content":"\\e112"},
			{"className":"o365i-callplus", "content":"\\e113"},
			{"className":"o365i-runningman", "content":"\\e114"},
			{"className":"o365i-commentplus", "content":"\\e115"},
			{"className":"o365i-arrowinwardstilt", "content":"\\e116"},
			{"className":"o365i-navigate", "content":"\\e117"},
			{"className":"o365i-delve", "content":"\\e118"},
			{"className":"o365i-photo", "content":"\\e119"},
			{"className":"o365i-filter", "content":"\\e11a"},
			{"className":"o365i-arrowoutwardstilt", "content":"\\e11b"},
			{"className":"o365i-shine", "content":"\\e11c"},
			{"className":"o365i-mail2", "content":"\\e11d"},
			{"className":"o365i-edit2", "content":"\\e11e"},
			{"className":"o365i-applauncher", "content":"\\e11f"},
			{"className":"o365i-building", "content":"\\e120"},
			{"className":"o365i-calendaritemrefresh", "content":"\\e121"},
			{"className":"o365i-cart", "content":"\\e122"},
			{"className":"o365i-commentlinks", "content":"\\e123"},
			{"className":"o365i-mappin", "content":"\\e124"},
			{"className":"o365i-orgchart", "content":"\\e125"},
			{"className":"o365i-geara", "content":"\\e130"},
			{"className":"o365i-gearc", "content":"\\e131"},
			{"className":"o365i-geard", "content":"\\e132"},
			{"className":"o365i-geare", "content":"\\e133"},
			{"className":"o365i-gearl", "content":"\\e134"},
			{"className":"o365i-gearm", "content":"\\e135"},
			{"className":"o365i-gearo", "content":"\\e136"},
			{"className":"o365i-gearp", "content":"\\e137"},
			{"className":"o365i-gears", "content":"\\e138"},
			{"className":"o365i-geary", "content":"\\e139"},
			{"className":"o365i-arrowleft", "content":"\\e150"},
			{"className":"o365i-arrowleft2", "content":"\\e152"},
			{"className":"o365i-calendaritemexlamation", "content":"\\e154"},
			{"className":"o365i-peoplemultiple", "content":"\\e155"},
			{"className":"o365i-officelogo", "content":"\\e160"},
			{"className":"o365i-money", "content":"\\e161"},
			{"className":"o365i-linegraph", "content":"\\e162"},
			{"className":"o365i-calendaritemedit", "content":"\\e163"},
			{"className":"o365i-gauge", "content":"\\e164"},
			{"className":"o365i-mailedit", "content":"\\e165"},
			{"className":"o365i-pin2", "content":"\\e167"},
			{"className":"o365i-onedriveplus", "content":"\\e168"},
			{"className":"o365i-heart", "content":"\\e16a"},
			{"className":"o365i-unheart", "content":"\\e16b"},
			{"className":"o365i-picture", "content":"\\e16c"},
			{"className":"o365i-cake", "content":"\\e16d"},
			{"className":"o365i-books", "content":"\\e16e"},
			{"className":"o365i-graph3", "content":"\\e16f"},
			{"className":"o365i-video", "content":"\\e170"},
			{"className":"o365i-soccor", "content":"\\e171"},
			{"className":"o365i-forkknife", "content":"\\e172"},
			{"className":"o365i-baloon", "content":"\\e173"},
			{"className":"o365i-cat", "content":"\\e174"},
			{"className":"o365i-poodle", "content":"\\e175"},
			{"className":"o365i-bag", "content":"\\e176"},
			{"className":"o365i-music", "content":"\\e177"},
			{"className":"o365i-stopwatch", "content":"\\e178"},
			{"className":"o365i-coffee", "content":"\\e179"},
			{"className":"o365i-briefcase", "content":"\\e17a"},
			{"className":"o365i-pill", "content":"\\e17b"},
			{"className":"o365i-trophie", "content":"\\e17c"},
			{"className":"o365i-medic", "content":"\\e17d"},
			{"className":"o365i-airplane", "content":"\\e17e"},
			{"className":"o365i-portratelayout", "content":"\\e17f"},
			{"className":"o365i-car", "content":"\\e180"},
			{"className":"o365i-dog", "content":"\\e181"},
			{"className":"o365i-file", "content":"\\e182"},
			{"className":"o365i-filedotted", "content":"\\e183"},
			{"className":"o365i-landscapelayout", "content":"\\e184"},
			{"className":"o365i-font", "content":"\\e185"},
			{"className":"o365i-inputstring", "content":"\\e186"},
			{"className":"o365i-inputnumber", "content":"\\e187"},
			{"className":"o365i-inputdropdown", "content":"\\e188"},
			{"className":"o365i-radio", "content":"\\e189"},
			{"className":"o365i-checkbox", "content":"\\e18a"},
			{"className":"o365i-openbook", "content":"\\e18b"},
			{"className":"o365i-bold", "content":"\\e18c"},
			{"className":"o365i-italic", "content":"\\e18d"},
			{"className":"o365i-underline", "content":"\\e18e"},
			{"className":"o365i-quotes", "content":"\\e18f"},
			{"className":"o365i-editfont", "content":"\\e190"},
			{"className":"o365i-pictureplus", "content":"\\e191"},
			{"className":"o365i-pictureminus", "content":"\\e192"},
			{"className":"o365i-computer", "content":"\\e193"},
			{"className":"o365i-tablet", "content":"\\e194"},
			{"className":"o365i-mobile", "content":"\\e195"},
			{"className":"o365i-calendar2", "content":"\\e196"},
			{"className":"o365i-eyecrossedout", "content":"\\e197"},
			{"className":"o365i-sheild", "content":"\\e198"},
			{"className":"o365i-skype", "content":"\\e199"},
			{"className":"o365i-h1", "content":"\\e19a"},
			{"className":"o365i-paint", "content":"\\e19b"}
		]
	},
	"glyphicon-icons": {
		"packageName":"Bootstrap Glyphicons",
		"url":"http://glyphicons.bootstrapcheatsheets.com/",
		"class":"glyphicon",
		"icons": [
			{"className":"glyphicon-asterisk"},
			{"className":"glyphicon-plus"},
			{"className":"glyphicon-euro"},
			{"className":"glyphicon-eur"},
			{"className":"glyphicon-minus"},
			{"className":"glyphicon-cloud"},
			{"className":"glyphicon-envelope"},
			{"className":"glyphicon-pencil"},
			{"className":"glyphicon-glass"},
			{"className":"glyphicon-music"},
			{"className":"glyphicon-search"},
			{"className":"glyphicon-heart"},
			{"className":"glyphicon-star"},
			{"className":"glyphicon-star-empty"},
			{"className":"glyphicon-user"},
			{"className":"glyphicon-film"},
			{"className":"glyphicon-th-large"},
			{"className":"glyphicon-th"},
			{"className":"glyphicon-th-list"},
			{"className":"glyphicon-ok"},
			{"className":"glyphicon-remove"},
			{"className":"glyphicon-zoom-in"},
			{"className":"glyphicon-zoom-out"},
			{"className":"glyphicon-off"},
			{"className":"glyphicon-signal"},
			{"className":"glyphicon-cog"},
			{"className":"glyphicon-trash"},
			{"className":"glyphicon-home"},
			{"className":"glyphicon-file"},
			{"className":"glyphicon-time"},
			{"className":"glyphicon-road"},
			{"className":"glyphicon-download-alt"},
			{"className":"glyphicon-download"},
			{"className":"glyphicon-upload"},
			{"className":"glyphicon-inbox"},
			{"className":"glyphicon-play-circle"},
			{"className":"glyphicon-repeat"},
			{"className":"glyphicon-refresh"},
			{"className":"glyphicon-list-alt"},
			{"className":"glyphicon-lock"},
			{"className":"glyphicon-flag"},
			{"className":"glyphicon-headphones"},
			{"className":"glyphicon-volume-off"},
			{"className":"glyphicon-volume-down"},
			{"className":"glyphicon-volume-up"},
			{"className":"glyphicon-qrcode"},
			{"className":"glyphicon-barcode"},
			{"className":"glyphicon-tag"},
			{"className":"glyphicon-tags"},
			{"className":"glyphicon-book"},
			{"className":"glyphicon-bookmark"},
			{"className":"glyphicon-print"},
			{"className":"glyphicon-camera"},
			{"className":"glyphicon-font"},
			{"className":"glyphicon-bold"},
			{"className":"glyphicon-italic"},
			{"className":"glyphicon-text-height"},
			{"className":"glyphicon-text-width"},
			{"className":"glyphicon-align-left"},
			{"className":"glyphicon-align-center"},
			{"className":"glyphicon-align-right"},
			{"className":"glyphicon-align-justify"},
			{"className":"glyphicon-list"},
			{"className":"glyphicon-indent-left"},
			{"className":"glyphicon-indent-right"},
			{"className":"glyphicon-facetime-video"},
			{"className":"glyphicon-picture"},
			{"className":"glyphicon-map-marker"},
			{"className":"glyphicon-adjust"},
			{"className":"glyphicon-tint"},
			{"className":"glyphicon-edit"},
			{"className":"glyphicon-share"},
			{"className":"glyphicon-check"},
			{"className":"glyphicon-move"},
			{"className":"glyphicon-step-backward"},
			{"className":"glyphicon-fast-backward"},
			{"className":"glyphicon-backward"},
			{"className":"glyphicon-play"},
			{"className":"glyphicon-pause"},
			{"className":"glyphicon-stop"},
			{"className":"glyphicon-forward"},
			{"className":"glyphicon-fast-forward"},
			{"className":"glyphicon-step-forward"},
			{"className":"glyphicon-eject"},
			{"className":"glyphicon-chevron-left"},
			{"className":"glyphicon-chevron-right"},
			{"className":"glyphicon-plus-sign"},
			{"className":"glyphicon-minus-sign"},
			{"className":"glyphicon-remove-sign"},
			{"className":"glyphicon-ok-sign"},
			{"className":"glyphicon-question-sign"},
			{"className":"glyphicon-info-sign"},
			{"className":"glyphicon-screenshot"},
			{"className":"glyphicon-remove-circle"},
			{"className":"glyphicon-ok-circle"},
			{"className":"glyphicon-ban-circle"},
			{"className":"glyphicon-arrow-left"},
			{"className":"glyphicon-arrow-right"},
			{"className":"glyphicon-arrow-up"},
			{"className":"glyphicon-arrow-down"},
			{"className":"glyphicon-share-alt"},
			{"className":"glyphicon-resize-full"},
			{"className":"glyphicon-resize-small"},
			{"className":"glyphicon-exclamation-sign"},
			{"className":"glyphicon-gift"},
			{"className":"glyphicon-leaf"},
			{"className":"glyphicon-fire"},
			{"className":"glyphicon-eye-open"},
			{"className":"glyphicon-eye-close"},
			{"className":"glyphicon-warning-sign"},
			{"className":"glyphicon-plane"},
			{"className":"glyphicon-calendar"},
			{"className":"glyphicon-random"},
			{"className":"glyphicon-comment"},
			{"className":"glyphicon-magnet"},
			{"className":"glyphicon-chevron-up"},
			{"className":"glyphicon-chevron-down"},
			{"className":"glyphicon-retweet"},
			{"className":"glyphicon-shopping-cart"},
			{"className":"glyphicon-folder-close"},
			{"className":"glyphicon-folder-open"},
			{"className":"glyphicon-resize-vertical"},
			{"className":"glyphicon-resize-horizontal"},
			{"className":"glyphicon-hdd"},
			{"className":"glyphicon-bullhorn"},
			{"className":"glyphicon-bell"},
			{"className":"glyphicon-certificate"},
			{"className":"glyphicon-thumbs-up"},
			{"className":"glyphicon-thumbs-down"},
			{"className":"glyphicon-hand-right"},
			{"className":"glyphicon-hand-left"},
			{"className":"glyphicon-hand-up"},
			{"className":"glyphicon-hand-down"},
			{"className":"glyphicon-circle-arrow-right"},
			{"className":"glyphicon-circle-arrow-left"},
			{"className":"glyphicon-circle-arrow-up"},
			{"className":"glyphicon-circle-arrow-down"},
			{"className":"glyphicon-globe"},
			{"className":"glyphicon-wrench"},
			{"className":"glyphicon-tasks"},
			{"className":"glyphicon-filter"},
			{"className":"glyphicon-briefcase"},
			{"className":"glyphicon-fullscreen"},
			{"className":"glyphicon-dashboard"},
			{"className":"glyphicon-paperclip"},
			{"className":"glyphicon-heart-empty"},
			{"className":"glyphicon-link"},
			{"className":"glyphicon-phone"},
			{"className":"glyphicon-pushpin"},
			{"className":"glyphicon-usd"},
			{"className":"glyphicon-gbp"},
			{"className":"glyphicon-sort"},
			{"className":"glyphicon-sort-by-alphabet"},
			{"className":"glyphicon-sort-by-alphabet-alt"},
			{"className":"glyphicon-sort-by-order"},
			{"className":"glyphicon-sort-by-order-alt"},
			{"className":"glyphicon-sort-by-attributes"},
			{"className":"glyphicon-sort-by-attributes-alt"},
			{"className":"glyphicon-unchecked"},
			{"className":"glyphicon-expand"},
			{"className":"glyphicon-collapse-down"},
			{"className":"glyphicon-collapse-up"},
			{"className":"glyphicon-log-in"},
			{"className":"glyphicon-flash"},
			{"className":"glyphicon-log-out"},
			{"className":"glyphicon-new-window"},
			{"className":"glyphicon-record"},
			{"className":"glyphicon-save"},
			{"className":"glyphicon-open"},
			{"className":"glyphicon-saved"},
			{"className":"glyphicon-import"},
			{"className":"glyphicon-export"},
			{"className":"glyphicon-send"},
			{"className":"glyphicon-floppy-disk"},
			{"className":"glyphicon-floppy-saved"},
			{"className":"glyphicon-floppy-remove"},
			{"className":"glyphicon-floppy-save"},
			{"className":"glyphicon-floppy-open"},
			{"className":"glyphicon-credit-card"},
			{"className":"glyphicon-transfer"},
			{"className":"glyphicon-cutlery"},
			{"className":"glyphicon-header"},
			{"className":"glyphicon-compressed"},
			{"className":"glyphicon-earphone"},
			{"className":"glyphicon-phone-alt"},
			{"className":"glyphicon-tower"},
			{"className":"glyphicon-stats"},
			{"className":"glyphicon-sd-video"},
			{"className":"glyphicon-hd-video"},
			{"className":"glyphicon-subtitles"},
			{"className":"glyphicon-sound-stereo"},
			{"className":"glyphicon-sound-dolby"},
			{"className":"glyphicon-sound-5-1"},
			{"className":"glyphicon-sound-6-1"},
			{"className":"glyphicon-sound-7-1"},
			{"className":"glyphicon-copyright-mark"},
			{"className":"glyphicon-registration-mark"},
			{"className":"glyphicon-cloud-download"},
			{"className":"glyphicon-cloud-upload"},
			{"className":"glyphicon-tree-conifer"},
			{"className":"glyphicon-tree-deciduous"},
			{"className":"glyphicon-cd"},
			{"className":"glyphicon-save-file"},
			{"className":"glyphicon-open-file"},
			{"className":"glyphicon-level-up"},
			{"className":"glyphicon-copy"},
			{"className":"glyphicon-paste"},
			{"className":"glyphicon-alert"},
			{"className":"glyphicon-equalizer"},
			{"className":"glyphicon-king"},
			{"className":"glyphicon-queen"},
			{"className":"glyphicon-pawn"},
			{"className":"glyphicon-bishop"},
			{"className":"glyphicon-knight"},
			{"className":"glyphicon-baby-formula"},
			{"className":"glyphicon-tent"},
			{"className":"glyphicon-blackboard"},
			{"className":"glyphicon-bed"},
			{"className":"glyphicon-apple"},
			{"className":"glyphicon-erase"},
			{"className":"glyphicon-hourglass"},
			{"className":"glyphicon-lamp"},
			{"className":"glyphicon-duplicate"},
			{"className":"glyphicon-piggy-bank"},
			{"className":"glyphicon-scissors"},
			{"className":"glyphicon-bitcoin"},
			{"className":"glyphicon-btc"},
			{"className":"glyphicon-xbt"},
			{"className":"glyphicon-yen"},
			{"className":"glyphicon-jpy"},
			{"className":"glyphicon-ruble"},
			{"className":"glyphicon-rub"},
			{"className":"glyphicon-scale"},
			{"className":"glyphicon-ice-lolly"},
			{"className":"glyphicon-ice-lolly-tasted"},
			{"className":"glyphicon-education"},
			{"className":"glyphicon-option-horizontal"},
			{"className":"glyphicon-option-vertical"},
			{"className":"glyphicon-menu-hamburger"},
			{"className":"glyphicon-modal-window"},
			{"className":"glyphicon-oil"},
			{"className":"glyphicon-grain"},
			{"className":"glyphicon-sunglasses"},
			{"className":"glyphicon-text-size"},
			{"className":"glyphicon-text-color"},
			{"className":"glyphicon-text-background"},
			{"className":"glyphicon-object-align-top"},
			{"className":"glyphicon-object-align-bottom"},
			{"className":"glyphicon-object-align-horizontal"},
			{"className":"glyphicon-object-align-left"},
			{"className":"glyphicon-object-align-vertical"},
			{"className":"glyphicon-object-align-right"},
			{"className":"glyphicon-triangle-right"},
			{"className":"glyphicon-triangle-left"},
			{"className":"glyphicon-triangle-bottom"},
			{"className":"glyphicon-triangle-top"},
			{"className":"glyphicon-console"},
			{"className":"glyphicon-superscript"},
			{"className":"glyphicon-subscript"},
			{"className":"glyphicon-menu-left"},
			{"className":"glyphicon-menu-right"},
			{"className":"glyphicon-menu-down"},
			{"className":"glyphicon-menu-up"}
		]
	},
	"ionicons": {
		"packageName":"IonIcons",
		"url":"http://ionicons.com/",
		"class":"ion",
		"icons": [
			{"className":"ion-alert"},
			{"className":"ion-alert-circled"},
			{"className":"ion-android-add"},
			{"className":"ion-android-add-circle"},
			{"className":"ion-android-alarm-clock"},
			{"className":"ion-android-alert"},
			{"className":"ion-android-apps"},
			{"className":"ion-android-archive"},
			{"className":"ion-android-arrow-back"},
			{"className":"ion-android-arrow-down"},
			{"className":"ion-android-arrow-dropdown"},
			{"className":"ion-android-arrow-dropdown-circle"},
			{"className":"ion-android-arrow-dropleft"},
			{"className":"ion-android-arrow-dropleft-circle"},
			{"className":"ion-android-arrow-dropright"},
			{"className":"ion-android-arrow-dropright-circle"},
			{"className":"ion-android-arrow-dropup"},
			{"className":"ion-android-arrow-dropup-circle"},
			{"className":"ion-android-arrow-forward"},
			{"className":"ion-android-arrow-up"},
			{"className":"ion-android-attach"},
			{"className":"ion-android-bar"},
			{"className":"ion-android-bicycle"},
			{"className":"ion-android-boat"},
			{"className":"ion-android-bookmark"},
			{"className":"ion-android-bulb"},
			{"className":"ion-android-bus"},
			{"className":"ion-android-calendar"},
			{"className":"ion-android-call"},
			{"className":"ion-android-camera"},
			{"className":"ion-android-cancel"},
			{"className":"ion-android-car"},
			{"className":"ion-android-cart"},
			{"className":"ion-android-chat"},
			{"className":"ion-android-checkbox"},
			{"className":"ion-android-checkbox-blank"},
			{"className":"ion-android-checkbox-outline"},
			{"className":"ion-android-checkbox-outline-blank"},
			{"className":"ion-android-checkmark-circle"},
			{"className":"ion-android-clipboard"},
			{"className":"ion-android-close"},
			{"className":"ion-android-cloud"},
			{"className":"ion-android-cloud-circle"},
			{"className":"ion-android-cloud-done"},
			{"className":"ion-android-cloud-outline"},
			{"className":"ion-android-color-palette"},
			{"className":"ion-android-compass"},
			{"className":"ion-android-contact"},
			{"className":"ion-android-contacts"},
			{"className":"ion-android-contract"},
			{"className":"ion-android-create"},
			{"className":"ion-android-delete"},
			{"className":"ion-android-desktop"},
			{"className":"ion-android-document"},
			{"className":"ion-android-done"},
			{"className":"ion-android-done-all"},
			{"className":"ion-android-download"},
			{"className":"ion-android-drafts"},
			{"className":"ion-android-exit"},
			{"className":"ion-android-expand"},
			{"className":"ion-android-favorite"},
			{"className":"ion-android-favorite-outline"},
			{"className":"ion-android-film"},
			{"className":"ion-android-folder"},
			{"className":"ion-android-folder-open"},
			{"className":"ion-android-funnel"},
			{"className":"ion-android-globe"},
			{"className":"ion-android-hand"},
			{"className":"ion-android-hangout"},
			{"className":"ion-android-happy"},
			{"className":"ion-android-home"},
			{"className":"ion-android-image"},
			{"className":"ion-android-laptop"},
			{"className":"ion-android-list"},
			{"className":"ion-android-locate"},
			{"className":"ion-android-lock"},
			{"className":"ion-android-mail"},
			{"className":"ion-android-map"},
			{"className":"ion-android-menu"},
			{"className":"ion-android-microphone"},
			{"className":"ion-android-microphone-off"},
			{"className":"ion-android-more-horizontal"},
			{"className":"ion-android-more-vertical"},
			{"className":"ion-android-navigate"},
			{"className":"ion-android-notifications"},
			{"className":"ion-android-notifications-none"},
			{"className":"ion-android-notifications-off"},
			{"className":"ion-android-open"},
			{"className":"ion-android-options"},
			{"className":"ion-android-people"},
			{"className":"ion-android-person"},
			{"className":"ion-android-person-add"},
			{"className":"ion-android-phone-landscape"},
			{"className":"ion-android-phone-portrait"},
			{"className":"ion-android-pin"},
			{"className":"ion-android-plane"},
			{"className":"ion-android-playstore"},
			{"className":"ion-android-print"},
			{"className":"ion-android-radio-button-off"},
			{"className":"ion-android-radio-button-on"},
			{"className":"ion-android-refresh"},
			{"className":"ion-android-remove"},
			{"className":"ion-android-remove-circle"},
			{"className":"ion-android-restaurant"},
			{"className":"ion-android-sad"},
			{"className":"ion-android-search"},
			{"className":"ion-android-send"},
			{"className":"ion-android-settings"},
			{"className":"ion-android-share"},
			{"className":"ion-android-share-alt"},
			{"className":"ion-android-star"},
			{"className":"ion-android-star-half"},
			{"className":"ion-android-star-outline"},
			{"className":"ion-android-stopwatch"},
			{"className":"ion-android-subway"},
			{"className":"ion-android-sunny"},
			{"className":"ion-android-sync"},
			{"className":"ion-android-textsms"},
			{"className":"ion-android-time"},
			{"className":"ion-android-train"},
			{"className":"ion-android-unlock"},
			{"className":"ion-android-upload"},
			{"className":"ion-android-volume-down"},
			{"className":"ion-android-volume-mute"},
			{"className":"ion-android-volume-off"},
			{"className":"ion-android-volume-up"},
			{"className":"ion-android-walk"},
			{"className":"ion-android-warning"},
			{"className":"ion-android-watch"},
			{"className":"ion-android-wifi"},
			{"className":"ion-aperture"},
			{"className":"ion-archive"},
			{"className":"ion-arrow-down-a"},
			{"className":"ion-arrow-down-b"},
			{"className":"ion-arrow-down-c"},
			{"className":"ion-arrow-expand"},
			{"className":"ion-arrow-graph-down-left"},
			{"className":"ion-arrow-graph-down-right"},
			{"className":"ion-arrow-graph-up-left"},
			{"className":"ion-arrow-graph-up-right"},
			{"className":"ion-arrow-left-a"},
			{"className":"ion-arrow-left-b"},
			{"className":"ion-arrow-left-c"},
			{"className":"ion-arrow-move"},
			{"className":"ion-arrow-resize"},
			{"className":"ion-arrow-return-left"},
			{"className":"ion-arrow-return-right"},
			{"className":"ion-arrow-right-a"},
			{"className":"ion-arrow-right-b"},
			{"className":"ion-arrow-right-c"},
			{"className":"ion-arrow-shrink"},
			{"className":"ion-arrow-swap"},
			{"className":"ion-arrow-up-a"},
			{"className":"ion-arrow-up-b"},
			{"className":"ion-arrow-up-c"},
			{"className":"ion-asterisk"},
			{"className":"ion-at"},
			{"className":"ion-backspace"},
			{"className":"ion-backspace-outline"},
			{"className":"ion-bag"},
			{"className":"ion-battery-charging"},
			{"className":"ion-battery-empty"},
			{"className":"ion-battery-full"},
			{"className":"ion-battery-half"},
			{"className":"ion-battery-low"},
			{"className":"ion-beaker"},
			{"className":"ion-beer"},
			{"className":"ion-bluetooth"},
			{"className":"ion-bonfire"},
			{"className":"ion-bookmark"},
			{"className":"ion-bowtie"},
			{"className":"ion-briefcase"},
			{"className":"ion-bug"},
			{"className":"ion-calculator"},
			{"className":"ion-calendar"},
			{"className":"ion-camera"},
			{"className":"ion-card"},
			{"className":"ion-cash"},
			{"className":"ion-chatbox"},
			{"className":"ion-chatbox-working"},
			{"className":"ion-chatboxes"},
			{"className":"ion-chatbubble"},
			{"className":"ion-chatbubble-working"},
			{"className":"ion-chatbubbles"},
			{"className":"ion-checkmark"},
			{"className":"ion-checkmark-circled"},
			{"className":"ion-checkmark-round"},
			{"className":"ion-chevron-down"},
			{"className":"ion-chevron-left"},
			{"className":"ion-chevron-right"},
			{"className":"ion-chevron-up"},
			{"className":"ion-clipboard"},
			{"className":"ion-clock"},
			{"className":"ion-close"},
			{"className":"ion-close-circled"},
			{"className":"ion-close-round"},
			{"className":"ion-closed-captioning"},
			{"className":"ion-cloud"},
			{"className":"ion-code"},
			{"className":"ion-code-download"},
			{"className":"ion-code-working"},
			{"className":"ion-coffee"},
			{"className":"ion-compass"},
			{"className":"ion-compose"},
			{"className":"ion-connection-bars"},
			{"className":"ion-contrast"},
			{"className":"ion-crop"},
			{"className":"ion-cube"},
			{"className":"ion-disc"},
			{"className":"ion-document"},
			{"className":"ion-document-text"},
			{"className":"ion-drag"},
			{"className":"ion-earth"},
			{"className":"ion-easel"},
			{"className":"ion-edit"},
			{"className":"ion-egg"},
			{"className":"ion-eject"},
			{"className":"ion-email"},
			{"className":"ion-email-unread"},
			{"className":"ion-erlenmeyer-flask"},
			{"className":"ion-erlenmeyer-flask-bubbles"},
			{"className":"ion-eye"},
			{"className":"ion-eye-disabled"},
			{"className":"ion-female"},
			{"className":"ion-filing"},
			{"className":"ion-film-marker"},
			{"className":"ion-fireball"},
			{"className":"ion-flag"},
			{"className":"ion-flame"},
			{"className":"ion-flash"},
			{"className":"ion-flash-off"},
			{"className":"ion-folder"},
			{"className":"ion-fork"},
			{"className":"ion-fork-repo"},
			{"className":"ion-forward"},
			{"className":"ion-funnel"},
			{"className":"ion-gear-a"},
			{"className":"ion-gear-b"},
			{"className":"ion-grid"},
			{"className":"ion-hammer"},
			{"className":"ion-happy"},
			{"className":"ion-happy-outline"},
			{"className":"ion-headphone"},
			{"className":"ion-heart"},
			{"className":"ion-heart-broken"},
			{"className":"ion-help"},
			{"className":"ion-help-buoy"},
			{"className":"ion-help-circled"},
			{"className":"ion-home"},
			{"className":"ion-icecream"},
			{"className":"ion-image"},
			{"className":"ion-images"},
			{"className":"ion-information"},
			{"className":"ion-information-circled"},
			{"className":"ion-ionic"},
			{"className":"ion-ios-alarm"},
			{"className":"ion-ios-alarm-outline"},
			{"className":"ion-ios-albums"},
			{"className":"ion-ios-albums-outline"},
			{"className":"ion-ios-americanfootball"},
			{"className":"ion-ios-americanfootball-outline"},
			{"className":"ion-ios-analytics"},
			{"className":"ion-ios-analytics-outline"},
			{"className":"ion-ios-arrow-back"},
			{"className":"ion-ios-arrow-down"},
			{"className":"ion-ios-arrow-forward"},
			{"className":"ion-ios-arrow-left"},
			{"className":"ion-ios-arrow-right"},
			{"className":"ion-ios-arrow-thin-down"},
			{"className":"ion-ios-arrow-thin-left"},
			{"className":"ion-ios-arrow-thin-right"},
			{"className":"ion-ios-arrow-thin-up"},
			{"className":"ion-ios-arrow-up"},
			{"className":"ion-ios-at"},
			{"className":"ion-ios-at-outline"},
			{"className":"ion-ios-barcode"},
			{"className":"ion-ios-barcode-outline"},
			{"className":"ion-ios-baseball"},
			{"className":"ion-ios-baseball-outline"},
			{"className":"ion-ios-basketball"},
			{"className":"ion-ios-basketball-outline"},
			{"className":"ion-ios-bell"},
			{"className":"ion-ios-bell-outline"},
			{"className":"ion-ios-body"},
			{"className":"ion-ios-body-outline"},
			{"className":"ion-ios-bolt"},
			{"className":"ion-ios-bolt-outline"},
			{"className":"ion-ios-book"},
			{"className":"ion-ios-book-outline"},
			{"className":"ion-ios-bookmarks"},
			{"className":"ion-ios-bookmarks-outline"},
			{"className":"ion-ios-box"},
			{"className":"ion-ios-box-outline"},
			{"className":"ion-ios-briefcase"},
			{"className":"ion-ios-briefcase-outline"},
			{"className":"ion-ios-browsers"},
			{"className":"ion-ios-browsers-outline"},
			{"className":"ion-ios-calculator"},
			{"className":"ion-ios-calculator-outline"},
			{"className":"ion-ios-calendar"},
			{"className":"ion-ios-calendar-outline"},
			{"className":"ion-ios-camera"},
			{"className":"ion-ios-camera-outline"},
			{"className":"ion-ios-cart"},
			{"className":"ion-ios-cart-outline"},
			{"className":"ion-ios-chatboxes"},
			{"className":"ion-ios-chatboxes-outline"},
			{"className":"ion-ios-chatbubble"},
			{"className":"ion-ios-chatbubble-outline"},
			{"className":"ion-ios-checkmark"},
			{"className":"ion-ios-checkmark-empty"},
			{"className":"ion-ios-checkmark-outline"},
			{"className":"ion-ios-circle-filled"},
			{"className":"ion-ios-circle-outline"},
			{"className":"ion-ios-clock"},
			{"className":"ion-ios-clock-outline"},
			{"className":"ion-ios-close"},
			{"className":"ion-ios-close-empty"},
			{"className":"ion-ios-close-outline"},
			{"className":"ion-ios-cloud"},
			{"className":"ion-ios-cloud-download"},
			{"className":"ion-ios-cloud-download-outline"},
			{"className":"ion-ios-cloud-outline"},
			{"className":"ion-ios-cloud-upload"},
			{"className":"ion-ios-cloud-upload-outline"},
			{"className":"ion-ios-cloudy"},
			{"className":"ion-ios-cloudy-night"},
			{"className":"ion-ios-cloudy-night-outline"},
			{"className":"ion-ios-cloudy-outline"},
			{"className":"ion-ios-cog"},
			{"className":"ion-ios-cog-outline"},
			{"className":"ion-ios-color-filter"},
			{"className":"ion-ios-color-filter-outline"},
			{"className":"ion-ios-color-wand"},
			{"className":"ion-ios-color-wand-outline"},
			{"className":"ion-ios-compose"},
			{"className":"ion-ios-compose-outline"},
			{"className":"ion-ios-contact"},
			{"className":"ion-ios-contact-outline"},
			{"className":"ion-ios-copy"},
			{"className":"ion-ios-copy-outline"},
			{"className":"ion-ios-crop"},
			{"className":"ion-ios-crop-strong"},
			{"className":"ion-ios-download"},
			{"className":"ion-ios-download-outline"},
			{"className":"ion-ios-drag"},
			{"className":"ion-ios-email"},
			{"className":"ion-ios-email-outline"},
			{"className":"ion-ios-eye"},
			{"className":"ion-ios-eye-outline"},
			{"className":"ion-ios-fastforward"},
			{"className":"ion-ios-fastforward-outline"},
			{"className":"ion-ios-filing"},
			{"className":"ion-ios-filing-outline"},
			{"className":"ion-ios-film"},
			{"className":"ion-ios-film-outline"},
			{"className":"ion-ios-flag"},
			{"className":"ion-ios-flag-outline"},
			{"className":"ion-ios-flame"},
			{"className":"ion-ios-flame-outline"},
			{"className":"ion-ios-flask"},
			{"className":"ion-ios-flask-outline"},
			{"className":"ion-ios-flower"},
			{"className":"ion-ios-flower-outline"},
			{"className":"ion-ios-folder"},
			{"className":"ion-ios-folder-outline"},
			{"className":"ion-ios-football"},
			{"className":"ion-ios-football-outline"},
			{"className":"ion-ios-game-controller-a"},
			{"className":"ion-ios-game-controller-a-outline"},
			{"className":"ion-ios-game-controller-b"},
			{"className":"ion-ios-game-controller-b-outline"},
			{"className":"ion-ios-gear"},
			{"className":"ion-ios-gear-outline"},
			{"className":"ion-ios-glasses"},
			{"className":"ion-ios-glasses-outline"},
			{"className":"ion-ios-grid-view"},
			{"className":"ion-ios-grid-view-outline"},
			{"className":"ion-ios-heart"},
			{"className":"ion-ios-heart-outline"},
			{"className":"ion-ios-help"},
			{"className":"ion-ios-help-empty"},
			{"className":"ion-ios-help-outline"},
			{"className":"ion-ios-home"},
			{"className":"ion-ios-home-outline"},
			{"className":"ion-ios-infinite"},
			{"className":"ion-ios-infinite-outline"},
			{"className":"ion-ios-information"},
			{"className":"ion-ios-information-empty"},
			{"className":"ion-ios-information-outline"},
			{"className":"ion-ios-ionic-outline"},
			{"className":"ion-ios-keypad"},
			{"className":"ion-ios-keypad-outline"},
			{"className":"ion-ios-lightbulb"},
			{"className":"ion-ios-lightbulb-outline"},
			{"className":"ion-ios-list"},
			{"className":"ion-ios-list-outline"},
			{"className":"ion-ios-location"},
			{"className":"ion-ios-location-outline"},
			{"className":"ion-ios-locked"},
			{"className":"ion-ios-locked-outline"},
			{"className":"ion-ios-loop"},
			{"className":"ion-ios-loop-strong"},
			{"className":"ion-ios-medical"},
			{"className":"ion-ios-medical-outline"},
			{"className":"ion-ios-medkit"},
			{"className":"ion-ios-medkit-outline"},
			{"className":"ion-ios-mic"},
			{"className":"ion-ios-mic-off"},
			{"className":"ion-ios-mic-outline"},
			{"className":"ion-ios-minus"},
			{"className":"ion-ios-minus-empty"},
			{"className":"ion-ios-minus-outline"},
			{"className":"ion-ios-monitor"},
			{"className":"ion-ios-monitor-outline"},
			{"className":"ion-ios-moon"},
			{"className":"ion-ios-moon-outline"},
			{"className":"ion-ios-more"},
			{"className":"ion-ios-more-outline"},
			{"className":"ion-ios-musical-note"},
			{"className":"ion-ios-musical-notes"},
			{"className":"ion-ios-navigate"},
			{"className":"ion-ios-navigate-outline"},
			{"className":"ion-ios-nutrition"},
			{"className":"ion-ios-nutrition-outline"},
			{"className":"ion-ios-paper"},
			{"className":"ion-ios-paper-outline"},
			{"className":"ion-ios-paperplane"},
			{"className":"ion-ios-paperplane-outline"},
			{"className":"ion-ios-partlysunny"},
			{"className":"ion-ios-partlysunny-outline"},
			{"className":"ion-ios-pause"},
			{"className":"ion-ios-pause-outline"},
			{"className":"ion-ios-paw"},
			{"className":"ion-ios-paw-outline"},
			{"className":"ion-ios-people"},
			{"className":"ion-ios-people-outline"},
			{"className":"ion-ios-person"},
			{"className":"ion-ios-person-outline"},
			{"className":"ion-ios-personadd"},
			{"className":"ion-ios-personadd-outline"},
			{"className":"ion-ios-photos"},
			{"className":"ion-ios-photos-outline"},
			{"className":"ion-ios-pie"},
			{"className":"ion-ios-pie-outline"},
			{"className":"ion-ios-pint"},
			{"className":"ion-ios-pint-outline"},
			{"className":"ion-ios-play"},
			{"className":"ion-ios-play-outline"},
			{"className":"ion-ios-plus"},
			{"className":"ion-ios-plus-empty"},
			{"className":"ion-ios-plus-outline"},
			{"className":"ion-ios-pricetag"},
			{"className":"ion-ios-pricetag-outline"},
			{"className":"ion-ios-pricetags"},
			{"className":"ion-ios-pricetags-outline"},
			{"className":"ion-ios-printer"},
			{"className":"ion-ios-printer-outline"},
			{"className":"ion-ios-pulse"},
			{"className":"ion-ios-pulse-strong"},
			{"className":"ion-ios-rainy"},
			{"className":"ion-ios-rainy-outline"},
			{"className":"ion-ios-recording"},
			{"className":"ion-ios-recording-outline"},
			{"className":"ion-ios-redo"},
			{"className":"ion-ios-redo-outline"},
			{"className":"ion-ios-refresh"},
			{"className":"ion-ios-refresh-empty"},
			{"className":"ion-ios-refresh-outline"},
			{"className":"ion-ios-reload"},
			{"className":"ion-ios-reverse-camera"},
			{"className":"ion-ios-reverse-camera-outline"},
			{"className":"ion-ios-rewind"},
			{"className":"ion-ios-rewind-outline"},
			{"className":"ion-ios-rose"},
			{"className":"ion-ios-rose-outline"},
			{"className":"ion-ios-search"},
			{"className":"ion-ios-search-strong"},
			{"className":"ion-ios-settings"},
			{"className":"ion-ios-settings-strong"},
			{"className":"ion-ios-shuffle"},
			{"className":"ion-ios-shuffle-strong"},
			{"className":"ion-ios-skipbackward"},
			{"className":"ion-ios-skipbackward-outline"},
			{"className":"ion-ios-skipforward"},
			{"className":"ion-ios-skipforward-outline"},
			{"className":"ion-ios-snowy"},
			{"className":"ion-ios-speedometer"},
			{"className":"ion-ios-speedometer-outline"},
			{"className":"ion-ios-star"},
			{"className":"ion-ios-star-half"},
			{"className":"ion-ios-star-outline"},
			{"className":"ion-ios-stopwatch"},
			{"className":"ion-ios-stopwatch-outline"},
			{"className":"ion-ios-sunny"},
			{"className":"ion-ios-sunny-outline"},
			{"className":"ion-ios-telephone"},
			{"className":"ion-ios-telephone-outline"},
			{"className":"ion-ios-tennisball"},
			{"className":"ion-ios-tennisball-outline"},
			{"className":"ion-ios-thunderstorm"},
			{"className":"ion-ios-thunderstorm-outline"},
			{"className":"ion-ios-time"},
			{"className":"ion-ios-time-outline"},
			{"className":"ion-ios-timer"},
			{"className":"ion-ios-timer-outline"},
			{"className":"ion-ios-toggle"},
			{"className":"ion-ios-toggle-outline"},
			{"className":"ion-ios-trash"},
			{"className":"ion-ios-trash-outline"},
			{"className":"ion-ios-undo"},
			{"className":"ion-ios-undo-outline"},
			{"className":"ion-ios-unlocked"},
			{"className":"ion-ios-unlocked-outline"},
			{"className":"ion-ios-upload"},
			{"className":"ion-ios-upload-outline"},
			{"className":"ion-ios-videocam"},
			{"className":"ion-ios-videocam-outline"},
			{"className":"ion-ios-volume-high"},
			{"className":"ion-ios-volume-low"},
			{"className":"ion-ios-wineglass"},
			{"className":"ion-ios-wineglass-outline"},
			{"className":"ion-ios-world"},
			{"className":"ion-ios-world-outline"},
			{"className":"ion-ipad"},
			{"className":"ion-iphone"},
			{"className":"ion-ipod"},
			{"className":"ion-jet"},
			{"className":"ion-key"},
			{"className":"ion-knife"},
			{"className":"ion-laptop"},
			{"className":"ion-leaf"},
			{"className":"ion-levels"},
			{"className":"ion-lightbulb"},
			{"className":"ion-link"},
			{"className":"ion-load-a"},
			{"className":"ion-load-b"},
			{"className":"ion-load-c"},
			{"className":"ion-load-d"},
			{"className":"ion-location"},
			{"className":"ion-lock-combination"},
			{"className":"ion-locked"},
			{"className":"ion-log-in"},
			{"className":"ion-log-out"},
			{"className":"ion-loop"},
			{"className":"ion-magnet"},
			{"className":"ion-male"},
			{"className":"ion-man"},
			{"className":"ion-map"},
			{"className":"ion-medkit"},
			{"className":"ion-merge"},
			{"className":"ion-mic-a"},
			{"className":"ion-mic-b"},
			{"className":"ion-mic-c"},
			{"className":"ion-minus"},
			{"className":"ion-minus-circled"},
			{"className":"ion-minus-round"},
			{"className":"ion-model-s"},
			{"className":"ion-monitor"},
			{"className":"ion-more"},
			{"className":"ion-mouse"},
			{"className":"ion-music-note"},
			{"className":"ion-navicon"},
			{"className":"ion-navicon-round"},
			{"className":"ion-navigate"},
			{"className":"ion-network"},
			{"className":"ion-no-smoking"},
			{"className":"ion-nuclear"},
			{"className":"ion-outlet"},
			{"className":"ion-paintbrush"},
			{"className":"ion-paintbucket"},
			{"className":"ion-paper-airplane"},
			{"className":"ion-paperclip"},
			{"className":"ion-pause"},
			{"className":"ion-person"},
			{"className":"ion-person-add"},
			{"className":"ion-person-stalker"},
			{"className":"ion-pie-graph"},
			{"className":"ion-pin"},
			{"className":"ion-pinpoint"},
			{"className":"ion-pizza"},
			{"className":"ion-plane"},
			{"className":"ion-planet"},
			{"className":"ion-play"},
			{"className":"ion-playstation"},
			{"className":"ion-plus"},
			{"className":"ion-plus-circled"},
			{"className":"ion-plus-round"},
			{"className":"ion-podium"},
			{"className":"ion-pound"},
			{"className":"ion-power"},
			{"className":"ion-pricetag"},
			{"className":"ion-pricetags"},
			{"className":"ion-printer"},
			{"className":"ion-pull-request"},
			{"className":"ion-qr-scanner"},
			{"className":"ion-quote"},
			{"className":"ion-radio-waves"},
			{"className":"ion-record"},
			{"className":"ion-refresh"},
			{"className":"ion-reply"},
			{"className":"ion-reply-all"},
			{"className":"ion-ribbon-a"},
			{"className":"ion-ribbon-b"},
			{"className":"ion-sad"},
			{"className":"ion-sad-outline"},
			{"className":"ion-scissors"},
			{"className":"ion-search"},
			{"className":"ion-settings"},
			{"className":"ion-share"},
			{"className":"ion-shuffle"},
			{"className":"ion-skip-backward"},
			{"className":"ion-skip-forward"},
			{"className":"ion-social-android"},
			{"className":"ion-social-android-outline"},
			{"className":"ion-social-angular"},
			{"className":"ion-social-angular-outline"},
			{"className":"ion-social-apple"},
			{"className":"ion-social-apple-outline"},
			{"className":"ion-social-bitcoin"},
			{"className":"ion-social-bitcoin-outline"},
			{"className":"ion-social-buffer"},
			{"className":"ion-social-buffer-outline"},
			{"className":"ion-social-chrome"},
			{"className":"ion-social-chrome-outline"},
			{"className":"ion-social-codepen"},
			{"className":"ion-social-codepen-outline"},
			{"className":"ion-social-css3"},
			{"className":"ion-social-css3-outline"},
			{"className":"ion-social-designernews"},
			{"className":"ion-social-designernews-outline"},
			{"className":"ion-social-dribbble"},
			{"className":"ion-social-dribbble-outline"},
			{"className":"ion-social-dropbox"},
			{"className":"ion-social-dropbox-outline"},
			{"className":"ion-social-euro"},
			{"className":"ion-social-euro-outline"},
			{"className":"ion-social-facebook"},
			{"className":"ion-social-facebook-outline"},
			{"className":"ion-social-foursquare"},
			{"className":"ion-social-foursquare-outline"},
			{"className":"ion-social-freebsd-devil"},
			{"className":"ion-social-github"},
			{"className":"ion-social-github-outline"},
			{"className":"ion-social-google"},
			{"className":"ion-social-google-outline"},
			{"className":"ion-social-googleplus"},
			{"className":"ion-social-googleplus-outline"},
			{"className":"ion-social-hackernews"},
			{"className":"ion-social-hackernews-outline"},
			{"className":"ion-social-html5"},
			{"className":"ion-social-html5-outline"},
			{"className":"ion-social-instagram"},
			{"className":"ion-social-instagram-outline"},
			{"className":"ion-social-javascript"},
			{"className":"ion-social-javascript-outline"},
			{"className":"ion-social-linkedin"},
			{"className":"ion-social-linkedin-outline"},
			{"className":"ion-social-markdown"},
			{"className":"ion-social-nodejs"},
			{"className":"ion-social-octocat"},
			{"className":"ion-social-pinterest"},
			{"className":"ion-social-pinterest-outline"},
			{"className":"ion-social-python"},
			{"className":"ion-social-reddit"},
			{"className":"ion-social-reddit-outline"},
			{"className":"ion-social-rss"},
			{"className":"ion-social-rss-outline"},
			{"className":"ion-social-sass"},
			{"className":"ion-social-skype"},
			{"className":"ion-social-skype-outline"},
			{"className":"ion-social-snapchat"},
			{"className":"ion-social-snapchat-outline"},
			{"className":"ion-social-tumblr"},
			{"className":"ion-social-tumblr-outline"},
			{"className":"ion-social-tux"},
			{"className":"ion-social-twitch"},
			{"className":"ion-social-twitch-outline"},
			{"className":"ion-social-twitter"},
			{"className":"ion-social-twitter-outline"},
			{"className":"ion-social-usd"},
			{"className":"ion-social-usd-outline"},
			{"className":"ion-social-vimeo"},
			{"className":"ion-social-vimeo-outline"},
			{"className":"ion-social-whatsapp"},
			{"className":"ion-social-whatsapp-outline"},
			{"className":"ion-social-windows"},
			{"className":"ion-social-windows-outline"},
			{"className":"ion-social-wordpress"},
			{"className":"ion-social-wordpress-outline"},
			{"className":"ion-social-yahoo"},
			{"className":"ion-social-yahoo-outline"},
			{"className":"ion-social-yen"},
			{"className":"ion-social-yen-outline"},
			{"className":"ion-social-youtube"},
			{"className":"ion-social-youtube-outline"},
			{"className":"ion-soup-can"},
			{"className":"ion-soup-can-outline"},
			{"className":"ion-speakerphone"},
			{"className":"ion-speedometer"},
			{"className":"ion-spoon"},
			{"className":"ion-star"},
			{"className":"ion-stats-bars"},
			{"className":"ion-steam"},
			{"className":"ion-stop"},
			{"className":"ion-thermometer"},
			{"className":"ion-thumbsdown"},
			{"className":"ion-thumbsup"},
			{"className":"ion-toggle"},
			{"className":"ion-toggle-filled"},
			{"className":"ion-transgender"},
			{"className":"ion-trash-a"},
			{"className":"ion-trash-b"},
			{"className":"ion-trophy"},
			{"className":"ion-tshirt"},
			{"className":"ion-tshirt-outline"},
			{"className":"ion-umbrella"},
			{"className":"ion-university"},
			{"className":"ion-unlocked"},
			{"className":"ion-upload"},
			{"className":"ion-usb"},
			{"className":"ion-videocamera"},
			{"className":"ion-volume-high"},
			{"className":"ion-volume-low"},
			{"className":"ion-volume-medium"},
			{"className":"ion-volume-mute"},
			{"className":"ion-wand"},
			{"className":"ion-waterdrop"},
			{"className":"ion-wifi"},
			{"className":"ion-wineglass"},
			{"className":"ion-woman"},
			{"className":"ion-wrench"},
			{"className":"ion-xbox"}
		]
	}
}